_geohash.py
geohash/__init__.py
geohash/geohash.py
geohash/geohash_build.py
geohash/geohash_build2.py
geohash/bin/linux/geohash.so
geohash/lib/linux/geohash.so
geohashcx-0.1.3.dist-info/AUTHORS.rst
geohashcx-0.1.3.dist-info/LICENSE
geohashcx-0.1.3.dist-info/METADATA
geohashcx-0.1.3.dist-info/WHEEL
geohashcx-0.1.3.dist-info/top_level.txt
geohashcx-0.1.3.dist-info/RECORD
