Metadata-Version: 2.1
Name: geohashcx
Version: 0.1.3
Summary: Encode/decode Geohashes http://geohash.org
Home-page: https://github.com/aldnav/geohash
Author: Aldrin Navarro
Author-email: aldrinnavarro16@gmail.com
License: GNU General Public License v3
Keywords: geohash
Platform: UNKNOWN
Classifier: Development Status :: 2 - Pre-Alpha
Classifier: Intended Audience :: Developers
Classifier: License :: OSI Approved :: GNU General Public License v3 (GPLv3)
Classifier: Natural Language :: English
Classifier: Programming Language :: Python :: 3
Classifier: Programming Language :: Python :: 3.4
Classifier: Programming Language :: Python :: 3.5
Classifier: Programming Language :: Python :: 3.6
Requires-Dist: cffi (>=1.12.3)
